setup.cfg
setup.py
figures_090807/__init__.py
figures_090807.egg-info/PKG-INFO
figures_090807.egg-info/SOURCES.txt
figures_090807.egg-info/dependency_links.txt
figures_090807.egg-info/not-zip-safe
figures_090807.egg-info/top_level.txt