Metadata-Version: 1.0
Name: figures-090807
Version: 0.1
Summary: Areas and Perimeters
Home-page: UNKNOWN
Author: UNKNOWN
Author-email: xoptka16@mail.ru
License: UNKNOWN
Platform: UNKNOWN
